setup.py
lastrun/__init__.py
lastrun.egg-info/PKG-INFO
lastrun.egg-info/SOURCES.txt
lastrun.egg-info/dependency_links.txt
lastrun.egg-info/top_level.txt
lastrun.egg-info/zip-safe