Metadata-Version: 1.0
Name: lastrun
Version: 0.1
Summary: Record the date and time a program was last run
Home-page: http://github.com/yowmamasita/lastrun
Author: Ben Sarmiento
Author-email: me@bensarmiento.com
License: MIT
Platform: UNKNOWN
